{"id":"KPIEF7GZ8JUMG","name":"小米商城 - 小米11 Ultra、Redmi K40 Pro、MIX FOLD，小米电视官方网站 (85)","size":2319,"btime":1622815455640,"mtime":1622815455655,"ext":"png","tags":[],"folders":["KPIEF5NP5T5ST"],"isDeleted":false,"url":"https://www.mi.com/search?keyword=%E5%B0%8F%E7%B1%B3%E8%B7%AF%E7%94%B1%E5%99%A8","annotation":"","modificationTime":1622815455230,"noThumbnail":true,"width":42,"height":42,"lastModified":1622815462956,"palettes":[{"color":[60,60,63],"ratio":62},{"color":[14,14,15],"ratio":12},{"color":[36,36,44],"ratio":5},{"color":[92,92,92],"ratio":4.78},{"color":[28,28,29],"ratio":4.1},{"color":[81,84,84],"ratio":3.75},{"color":[36,36,36],"ratio":2.73},{"color":[135,135,135],"ratio":2.39},{"color":[60,96,100],"ratio":0.68},{"color":[108,108,108],"ratio":0.34},{"color":[76,76,84],"ratio":0.34}]}